celery-stubs/__init__.pyi
celery-stubs/__main__.pyi
celery-stubs/_state.pyi
celery-stubs/beat.pyi
celery-stubs/bootsteps.pyi
celery-stubs/canvas.pyi
celery-stubs/exceptions.pyi
celery-stubs/five.pyi
celery-stubs/local.pyi
celery-stubs/platforms.pyi
celery-stubs/result.pyi
celery-stubs/schedules.pyi
celery-stubs/signals.pyi
celery-stubs/states.pyi
celery-stubs/app/__init__.pyi
celery-stubs/app/amqp.pyi
celery-stubs/app/annotations.pyi
celery-stubs/app/backends.pyi
celery-stubs/app/base.pyi
celery-stubs/app/builtins.pyi
celery-stubs/app/control.pyi
celery-stubs/app/defaults.pyi
celery-stubs/app/events.pyi
celery-stubs/app/log.pyi
celery-stubs/app/registry.pyi
celery-stubs/app/routes.pyi
celery-stubs/app/task.pyi
celery-stubs/app/trace.pyi
celery-stubs/app/utils.pyi
celery-stubs/apps/__init__.pyi
celery-stubs/apps/beat.pyi
celery-stubs/apps/multi.pyi
celery-stubs/apps/worker.pyi
celery-stubs/backends/__init__.pyi
celery-stubs/backends/amqp.pyi
celery-stubs/backends/arangodb.pyi
celery-stubs/backends/asynchronous.pyi
celery-stubs/backends/azureblockblob.pyi
celery-stubs/backends/base.pyi
celery-stubs/backends/cache.pyi
celery-stubs/backends/cassandra.pyi
celery-stubs/backends/consul.pyi
celery-stubs/backends/cosmosdbsql.pyi
celery-stubs/backends/couchbase.pyi
celery-stubs/backends/couchdb.pyi
celery-stubs/backends/dynamodb.pyi
celery-stubs/backends/elasticsearch.pyi
celery-stubs/backends/filesystem.pyi
celery-stubs/backends/mongodb.pyi
celery-stubs/backends/redis.pyi
celery-stubs/backends/riak.pyi
celery-stubs/backends/rpc.pyi
celery-stubs/backends/s3.pyi
celery-stubs/backends/database/__init__.pyi
celery-stubs/backends/database/models.pyi
celery-stubs/backends/database/session.pyi
celery-stubs/bin/__init__.pyi
celery-stubs/bin/amqp.pyi
celery-stubs/bin/base.pyi
celery-stubs/bin/beat.pyi
celery-stubs/bin/call.pyi
celery-stubs/bin/celery.pyi
celery-stubs/bin/celeryd_detach.pyi
celery-stubs/bin/control.pyi
celery-stubs/bin/events.pyi
celery-stubs/bin/graph.pyi
celery_stubs-0.1.3.dist-info/METADATA
celery_stubs-0.1.3.dist-info/WHEEL
celery_stubs-0.1.3.dist-info/top_level.txt
celery_stubs-0.1.3.dist-info/RECORD
