Metadata-Version: 2.1
Name: celery-stubs
Version: 0.1.3
Summary: celery stubs
Home-page: https://github.com/ryanwang520/celery-stubs
Author: Ryan Wang
Author-email: hwwangwang@gmail.com
License: MIT License
Classifier: Development Status :: 3 - Alpha
Classifier: Programming Language :: Python :: 3
